Metadata-Version: 2.1
Name: CRISPR-HMM
Version: 1.0.0
Summary: Sequence alignment of CRISPR mutation data with hidden Markov model.
Home-page: https://github.com/JasperYH/CRISPR-HMM
Author: Jingyuan Hu
Author-email: Jingyuan Hu <jingyuan@ds.dfci.harvard.edu>
Classifier: Programming Language :: Python :: 3
Classifier: License :: OSI Approved :: MIT License
Classifier: Operating System :: OS Independent
License-File: LICENSE
